[{"roomName": "C1.112", "course": "Heuristieken 1", "roomSize": 60, "startTime": 6, "students": [["Abdallah Beulen", "22871048"], ["Vivianne Buter", "86807027"], ["Andr\u00e9 Dieters", "57467488"], ["Mattie Eisinga", "59075181"], ["Belle Florijn", "14941752"], ["Sahar Hamstra", "71839156"], ["Ytje Hup", "87210640"], ["Geartsje Jackson", "45660925"], ["Kyan Jankie", "66122625"], ["Nuriye Kooijmans", "75997788"], ["Machteld Kwantes", "97417002"], ["Mathyn Lamme", "31897288"], ["Hetty Lindhout", "1696500"], ["Marcellus Mijnheer", "4783858"], ["Jo-Anne Modderkolk", "56749879"], ["Geurt Nuiten", "61060652"], ["Timo Postuma", "36903574"], ["Andr\u00e9 Putters", "37110913"], ["Jarik Regeling", "4353500"], ["Tea Rutte", "76393508"], ["Imran Scheffers", "48357272"], ["Emrah Schrama", "44901052"], ["Mich\u00e8l Sieben", "83443653"], ["No\u00eb Slangen", "92977271"], ["Shaya Snelder", "19858730"], ["Maan ten Pas", "20331158"], ["Pleun ter Heide", "4568018"], ["Sarena Tjeerdsma", "14591033"], ["Emme Udo", "42171678"], ["Keely Ursem", "14816774"], ["Dineke Valster", "20830477"], ["Cherilyn van Amelsvoort", "97019450"], ["Cyrano van den Eijnde", "81218347"], ["Cleo van Rietschoten", "79879876"], ["Georgia van Rossem", "58736785"], ["Elske van Suijlekom", "11996292"], ["Hui van Zeijl", "14138904"], ["Kavish Versteeg", "22323043"], ["Karim Vingerhoets", "98105190"], ["Tjesse Voesten", "13658563"], ["Zhen Vullings", "53775014"], ["Harke Wester", "53107172"], ["Ay\u00e7a Woertman", "75521763"], ["Juno Zaaijer", "94930277"]], "day": "tu", "validity": "True", "workType": "lecture"}, {"roomName": "C0.110", "course": "Heuristieken 1", "roomSize": 117, "startTime": 0, "students": [["Abdallah Beulen", "22871048"], ["Vivianne Buter", "86807027"], ["Andr\u00e9 Dieters", "57467488"], ["Mattie Eisinga", "59075181"], ["Belle Florijn", "14941752"], ["Sahar Hamstra", "71839156"], ["Ytje Hup", "87210640"], ["Geartsje Jackson", "45660925"], ["Kyan Jankie", "66122625"], ["Nuriye Kooijmans", "75997788"], ["Machteld Kwantes", "97417002"], ["Mathyn Lamme", "31897288"], ["Hetty Lindhout", "1696500"], ["Marcellus Mijnheer", "4783858"], ["Jo-Anne Modderkolk", "56749879"], ["Geurt Nuiten", "61060652"], ["Timo Postuma", "36903574"], ["Andr\u00e9 Putters", "37110913"], ["Jarik Regeling", "4353500"], ["Tea Rutte", "76393508"], ["Imran Scheffers", "48357272"], ["Emrah Schrama", "44901052"], ["Mich\u00e8l Sieben", "83443653"], ["No\u00eb Slangen", "92977271"], ["Shaya Snelder", "19858730"], ["Maan ten Pas", "20331158"], ["Pleun ter Heide", "4568018"], ["Sarena Tjeerdsma", "14591033"], ["Emme Udo", "42171678"], ["Keely Ursem", "14816774"], ["Dineke Valster", "20830477"], ["Cherilyn van Amelsvoort", "97019450"], ["Cyrano van den Eijnde", "81218347"], ["Cleo van Rietschoten", "79879876"], ["Georgia van Rossem", "58736785"], ["Elske van Suijlekom", "11996292"], ["Hui van Zeijl", "14138904"], ["Kavish Versteeg", "22323043"], ["Karim Vingerhoets", "98105190"], ["Tjesse Voesten", "13658563"], ["Zhen Vullings", "53775014"], ["Harke Wester", "53107172"], ["Ay\u00e7a Woertman", "75521763"], ["Juno Zaaijer", "94930277"]], "day": "tu", "validity": "False", "workType": "seminar"}]