[{"roomName": "A1.08", "course": "Programmeren in Java 2", "roomSize": 20, "startTime": 2, "students": ["Jayme van Eeuwijk"], "day": "fr", "validity": "True", "workType": "practicum"}, {"roomName": "A1.06", "course": "Data Mining", "roomSize": 22, "startTime": 6, "students": ["Jayme van Eeuwijk"], "day": "th", "validity": "True", "workType": "practicum"}, {"roomName": "C1.112", "course": "Data Mining", "roomSize": 60, "startTime": 4, "students": ["Jayme van Eeuwijk"], "day": "mo", "validity": "True", "workType": "lecture"}, {"roomName": "A1.08", "course": "Data Mining", "roomSize": 20, "startTime": 4, "students": ["Jayme van Eeuwijk"], "day": "tu", "validity": "True", "workType": "seminar"}, {"roomName": "B0.201", "course": "Data Mining", "roomSize": 48, "startTime": 0, "students": ["Jayme van Eeuwijk"], "day": "fr", "validity": "True", "workType": "lecture"}, {"roomName": "A1.06", "course": "Project Numerical Recipes", "roomSize": 22, "startTime": 0, "students": ["Jayme van Eeuwijk"], "day": "fr", "validity": "True", "workType": "practicum"}]