[{"roomName": "A1.08", "course": "Informatie- en organisatieontwerp", "roomSize": 20, "startTime": 4, "students": ["Abd\u00fcl Buth"], "day": "fr", "validity": "True", "workType": "practicum"}, {"roomName": "C1.112", "course": "Architectuur en computerorganisatie", "roomSize": 60, "startTime": 6, "students": ["Abd\u00fcl Buth"], "day": "th", "validity": "True", "workType": "lecture"}, {"roomName": "B0.201", "course": "Informatie- en organisatieontwerp", "roomSize": 48, "startTime": 6, "students": ["Abd\u00fcl Buth"], "day": "tu", "validity": "True", "workType": "seminar"}, {"roomName": "A1.06", "course": "Informatie- en organisatieontwerp", "roomSize": 22, "startTime": 4, "students": ["Abd\u00fcl Buth"], "day": "mo", "validity": "True", "workType": "lecture"}, {"roomName": "A1.06", "course": "Informatie- en organisatieontwerp", "roomSize": 22, "startTime": 4, "students": ["Abd\u00fcl Buth"], "day": "fr", "validity": "True", "workType": "lecture"}, {"roomName": "A1.08", "course": "Architectuur en computerorganisatie", "roomSize": 20, "startTime": 6, "students": ["Abd\u00fcl Buth"], "day": "we", "validity": "True", "workType": "lecture"}]