[{"roomName": "C1.112", "course": "Algoritmen en complexiteit", "roomSize": 60, "startTime": 6, "students": ["Solane Paulissen"], "day": "mo", "validity": "True", "workType": "lecture"}, {"roomName": "A1.10", "course": "Collectieve Intelligentie", "roomSize": 56, "startTime": 2, "students": ["Solane Paulissen"], "day": "th", "validity": "True", "workType": "practicum"}, {"roomName": "B0.201", "course": "Algoritmen en complexiteit", "roomSize": 48, "startTime": 0, "students": ["Solane Paulissen"], "day": "th", "validity": "True", "workType": "practicum"}, {"roomName": "C1.112", "course": "Collectieve Intelligentie", "roomSize": 60, "startTime": 2, "students": ["Solane Paulissen"], "day": "we", "validity": "True", "workType": "seminar"}, {"roomName": "B0.201", "course": "Algoritmen en complexiteit", "roomSize": 48, "startTime": 6, "students": ["Solane Paulissen"], "day": "mo", "validity": "True", "workType": "seminar"}, {"roomName": "C0.110", "course": "Collectieve Intelligentie", "roomSize": 117, "startTime": 4, "students": ["Solane Paulissen"], "day": "fr", "validity": "True", "workType": "lecture"}, {"roomName": "A1.06", "course": "Compilerbouw practicum", "roomSize": 22, "startTime": 2, "students": ["Solane Paulissen"], "day": "we", "validity": "True", "workType": "practicum"}, {"roomName": "C0.110", "course": "Collectieve Intelligentie", "roomSize": 117, "startTime": 4, "students": ["Solane Paulissen"], "day": "mo", "validity": "True", "workType": "lecture"}, {"roomName": "A1.10", "course": "Collectieve Intelligentie", "roomSize": 56, "startTime": 6, "students": ["Solane Paulissen"], "day": "th", "validity": "True", "workType": "lecture"}]