[{"roomName": "C0.110", "course": "Calculus 2", "roomSize": 117, "startTime": 0, "students": ["Or\u00e7un Sterenberg"], "day": "mo", "validity": "True", "workType": "lecture0"}, {"roomName": "B0.201", "course": "Calculus 2", "roomSize": 48, "startTime": 2, "students": ["Or\u00e7un Sterenberg"], "day": "mo", "validity": "True", "workType": "seminar0"}, {"roomName": "A1.10", "course": "Compilerbouw", "roomSize": 56, "startTime": 2, "students": ["Or\u00e7un Sterenberg"], "day": "tu", "validity": "True", "workType": "lecture0"}, {"roomName": "C0.110", "course": "Compilerbouw", "roomSize": 117, "startTime": 4, "students": ["Or\u00e7un Sterenberg"], "day": "th", "validity": "True", "workType": "lecture1"}, {"roomName": "C1.112", "course": "Compilerbouw", "roomSize": 60, "startTime": 6, "students": ["Or\u00e7un Sterenberg"], "day": "th", "validity": "True", "workType": "seminar0"}, {"roomName": "C1.112", "course": "Compilerbouw", "roomSize": 60, "startTime": 0, "students": ["Or\u00e7un Sterenberg"], "day": "mo", "validity": "True", "workType": "practicum0"}, {"roomName": "B0.201", "course": "Programmeren in Java 2", "roomSize": 48, "startTime": 4, "students": ["Or\u00e7un Sterenberg"], "day": "tu", "validity": "True", "workType": "practicum0"}]