[{"roomName": "B0.201", "course": "Bioinformatica", "roomSize": 48, "startTime": 0, "students": ["Owen Jama"], "day": "we", "validity": "True", "workType": "lecture0"}, {"roomName": "A1.10", "course": "Bioinformatica", "roomSize": 56, "startTime": 0, "students": ["Owen Jama"], "day": "tu", "validity": "True", "workType": "lecture1"}, {"roomName": "A1.10", "course": "Bioinformatica", "roomSize": 56, "startTime": 6, "students": ["Owen Jama"], "day": "th", "validity": "True", "workType": "lecture2"}, {"roomName": "A1.04", "course": "Bioinformatica", "roomSize": 41, "startTime": 0, "students": ["Owen Jama"], "day": "mo", "validity": "True", "workType": "seminar0"}, {"roomName": "A1.06", "course": "Bioinformatica", "roomSize": 22, "startTime": 4, "students": ["Owen Jama"], "day": "we", "validity": "True", "workType": "practicum0"}, {"roomName": "A1.08", "course": "Zoeken sturen en bewegen", "roomSize": 20, "startTime": 4, "students": ["Owen Jama"], "day": "mo", "validity": "True", "workType": "practicum0"}]