[{"roomName": "C1.112", "course": "Moderne Databases", "roomSize": 60, "startTime": 2, "students": ["Hande Essink"], "day": "we", "validity": "True", "workType": "lecture0"}, {"roomName": "B0.201", "course": "Moderne Databases", "roomSize": 48, "startTime": 4, "students": ["Hande Essink"], "day": "th", "validity": "True", "workType": "seminar0"}, {"roomName": "C0.110", "course": "Moderne Databases", "roomSize": 117, "startTime": 2, "students": ["Hande Essink"], "day": "fr", "validity": "True", "workType": "practicum0"}]